mle_toolbox/__init__.py
mle_toolbox/_version.py
mle_toolbox/experiment.py
mle_toolbox/toolbox.py
mle_toolbox/hyperopt/__init__.py
mle_toolbox/hyperopt/hyper_logger.py
mle_toolbox/hyperopt/mle_batch_search.py
mle_toolbox/launch/__init__.py
mle_toolbox/launch/launch_experiment.py
mle_toolbox/launch/multi_config.py
mle_toolbox/launch/prepare_experiment.py
mle_toolbox/launch/processing_job.py
mle_toolbox/launch/search_experiment.py
mle_toolbox/launch/single_config.py
mle_toolbox/launch/spawn_jobs.py
mle_toolbox/report/__init__.py
mle_toolbox/report/generate_figures.py
mle_toolbox/report/generate_markdown.py
mle_toolbox/report/generate_reports.py
mle_toolbox/src/__init__.py
mle_toolbox/src/initialize.py
mle_toolbox/src/monitor.py
mle_toolbox/src/project.py
mle_toolbox/src/protocol.py
mle_toolbox/src/report.py
mle_toolbox/src/retrieve.py
mle_toolbox/src/run.py
mle_toolbox/src/sync.py
mle_toolbox/utils/__init__.py
mle_toolbox/utils/core_experiment.py
mle_toolbox/utils/core_files_load.py
mle_toolbox/utils/helpers.py
mle_toolbox/utils/hyper_log.py
mle_toolbox/utils/protocol_data.py
mle_toolbox/visualize/__init__.py
mle_toolbox/visualize/dynamic_1d_anims.py
mle_toolbox/visualize/dynamic_2d_grid.py
mle_toolbox/visualize/dynamic_2d_scatter.py
mle_toolbox/visualize/dynamic_3d_scatter.py
mle_toolbox/visualize/dynamic_3d_surface.py
mle_toolbox/visualize/static_1d_plots.py
mle_toolbox/visualize/static_2d_plots.py
mle_toolbox/visualize/toolbox.mplstyle
mle_toolbox-0.3.5.dist-info/LICENSE
mle_toolbox-0.3.5.dist-info/METADATA
mle_toolbox-0.3.5.dist-info/WHEEL
mle_toolbox-0.3.5.dist-info/entry_points.txt
mle_toolbox-0.3.5.dist-info/top_level.txt
mle_toolbox-0.3.5.dist-info/RECORD
