Metadata-Version: 2.1
Name: mle_toolbox
Version: 0.3.5
Summary: Machine Learning Experiment Toolbox
Home-page: https://github.com/mle-infrastructure/mle-toolbox
Download-URL: https://github.com/mle-infrastructure/mle-toolbox/archive/v0.3.5.tar.gz
Author: Robert Tjarko Lange
Author-email: robertlange0@gmail.com
Platform: any
Classifier: Programming Language :: Python :: 3.7
Classifier: Programming Language :: Python :: 3.8
Classifier: Programming Language :: Python :: 3.9
Classifier: License :: OSI Approved :: MIT License
Classifier: Operating System :: OS Independent
Classifier: Topic :: Scientific/Engineering :: Artificial Intelligence
Requires-Python: >=3.7
License-File: LICENSE
Requires-Dist: numpy
Requires-Dist: pandas
Requires-Dist: dotmap
Requires-Dist: h5py
Requires-Dist: toml
Requires-Dist: pyyaml
Requires-Dist: pickle5
Requires-Dist: rich
Requires-Dist: mle-logging
Requires-Dist: mle-hyperopt
Requires-Dist: mle-scheduler
Requires-Dist: mle-monitor
Provides-Extra: examples
Requires-Dist: torch; extra == "examples"
Requires-Dist: google-cloud-storage; extra == "examples"
Requires-Dist: matplotlib; extra == "examples"
Requires-Dist: seaborn; extra == "examples"
Requires-Dist: nevergrad; extra == "examples"
Provides-Extra: full
Requires-Dist: markdown2; extra == "full"
Requires-Dist: xhtml2pdf; extra == "full"
Requires-Dist: matplotlib; extra == "full"
Requires-Dist: seaborn; extra == "full"
Requires-Dist: statsmodels; extra == "full"
Requires-Dist: slack-clusterbot; extra == "full"
Requires-Dist: mle-monitor[full]; extra == "full"
Requires-Dist: mle-hyperopt[full]; extra == "full"
Requires-Dist: mle-scheduler[full]; extra == "full"
